qr_scangen/ScanGen.py
qr_scangen/__init__.py
qr_scangen/__main__.py
qr_scangen/clipboard.py
qr_scangen/convert_to_py.py
qr_scangen/main.py
qr_scangen/wifi_utils.py
qr_scangen-1.4.2.dist-info/licenses/LICENSE
qr_scangen-1.4.2.dist-info/licenses/LICENSE-CC0
qr_scangen-1.4.2.dist-info/METADATA
qr_scangen-1.4.2.dist-info/WHEEL
qr_scangen-1.4.2.dist-info/entry_points.txt
qr_scangen-1.4.2.dist-info/top_level.txt
qr_scangen-1.4.2.dist-info/RECORD
