Metadata-Version: 2.4
Name: QR-ScanGen
Version: 1.4.2
Summary: A simple cross-platform QR code scanner and generator
Author-email: Emendir <dev@emendir.tech>
License-Expression: MIT-0 OR CC0-1.0
Project-URL: Homepage, https://github.com/emendir/QR-ScanGen
Project-URL: Repository, https://github.com/emendir/QR-ScanGen
Project-URL: Issues, https://github.com/emendir/QR-ScanGen/issues
Project-URL: Donate, https://emendir.tech/Donate.html
License-File: LICENSE
License-File: LICENSE-CC0
Requires-Dist: meson-python
Requires-Dist: scikit-build
Requires-Dist: sdbus-networkmanager; sys_platform == "linux"
Requires-Dist: comtypes; sys_platform == "windows"
Requires-Dist: numpy
Requires-Dist: opencv_python
Requires-Dist: Pillow==10.4.0
Requires-Dist: pyperclip
Requires-Dist: pywifi
Requires-Dist: pyzbar==0.1.9
Requires-Dist: qrcode
Requires-Dist: PyQt6
Dynamic: license-file
